imhere/__init__.py
imhere/imhere.py
imhere/utils.py
imhere-0.1.0.dist-info/LICENSE
imhere-0.1.0.dist-info/WHEEL
imhere-0.1.0.dist-info/METADATA
imhere-0.1.0.dist-info/RECORD
