Metadata-Version: 2.1
Name: imhere
Version: 0.1.0
Summary: ImHere, simple log for simple debug
License: MIT
Author: rojack96
Author-email: cerroberto96@gmail.com
Requires-Python: >=3.8,<4.0
Classifier: License :: OSI Approved :: MIT License
Classifier: Programming Language :: Python :: 3
Classifier: Programming Language :: Python :: 3.10
Classifier: Programming Language :: Python :: 3.8
Classifier: Programming Language :: Python :: 3.9
